{"images": [], "names": [{"name": "Traversine", "origin": "Unknown", "link": "", "primary": true}, {"name": "Tr\u00e9cyne", "origin": "French?", "link": "", "primary": false}], "description": "Mentioned only by Williams, who says: \ufffdThe Tr\u00e9cyne at St S\u00e9verin, Paris, 1626, was probably a Traversine or small flute 2'.\ufffd.", "construction": "", "usage": "", "variants": [], "comparisons": [], "examplesDescription": "Osiris contains two examples of Traversine, and none of Tr\u00e9cyne. Contributions welcome.", "examples": [{"link": "", "name": "Traversine 2', Hoofdwerk; St. Gorikskerk, Brussels, Belgium; Balders 1686."}, {"link": "", "name": "Traversine 2', Manual I; Cathedrale, Metz, France; Treves 1536. Reconstructed by Garnier in 1982."}], "soundClips": [], "bibliography": []}