{"images": [], "names": [{"name": "Dulcis", "origin": "Latin", "link": "", "primary": false}], "description": "Mentioned only in Grove, who says: \ufffdThe verbal coincidence of Dolce, Dolcan, Dulciana and Dulzian has led to much confusion; probably all terms derive from Dulcis, a stop with \ufffdsweet\ufffd tone.\ufffd The Latin word dulcis means \ufffddelightful, sweet, pleasant, or agreeable\ufffd.", "construction": "", "usage": "", "variants": [], "comparisons": [], "examplesDescription": "None known.", "examples": [], "soundClips": [], "bibliography": []}