{"images": [], "names": [{"name": "Kleinregalbass", "origin": "German", "link": "", "primary": false}], "description": "A Kleinregal that appears in the pedal.", "construction": "", "usage": "", "variants": [], "comparisons": [], "examplesDescription": "Kleinregalbass 2', Pedal; St. Dominicus, Prag [sic; Prague, Czechoslovakia?]. This example, cited by Adlung, is the only one known.", "examples": [{"link": "", "name": "Kleinregalbass 2', Pedal; St. Dominicus, Prag [sic; Prague, Czechoslovakia?]. This example, cited by Adlung, is the only one known."}], "soundClips": [], "bibliography": []}